scrapy_warcio/__init__.py
scrapy_warcio/warcio.py
scrapy_warcio-0.0.8.data/data/middlewares.py
scrapy_warcio-0.0.8.data/data/settings.yml
scrapy_warcio-0.0.8.dist-info/METADATA
scrapy_warcio-0.0.8.dist-info/WHEEL
scrapy_warcio-0.0.8.dist-info/top_level.txt
scrapy_warcio-0.0.8.dist-info/RECORD
