Metadata-Version: 2.1
Name: scrapy-warcio
Version: 0.0.8
Summary: Scrapy WARC I/O
Home-page: https://github.com/internetarchive/scrapy-warcio
Author: Steve Sisney
Author-email: steve@archive.org
License: UNKNOWN
Platform: UNKNOWN
Classifier: Programming Language :: Python :: 3
Classifier: Operating System :: OS Independent
Requires-Dist: python-magic
Requires-Dist: pyyaml
Requires-Dist: scrapy
Requires-Dist: warctools
